git_gud-0.4.5.data/data/man/man1/git-gud.1
gitgud/__init__.py
gitgud/__main__.py
gitgud/conftest.py
gitgud/version.txt
gitgud/hooks/__init__.py
gitgud/hooks/postrewrite.py
gitgud/skills/__init__.py
gitgud/skills/basics/__init__.py
gitgud/skills/basics/test_levels.py
gitgud/skills/basics/_branching/explanation.txt
gitgud/skills/basics/_branching/goal.txt
gitgud/skills/basics/_branching/setup.spec
gitgud/skills/basics/_branching/solution.txt
gitgud/skills/basics/_branching/test.spec
gitgud/skills/basics/_committing/explanation.txt
gitgud/skills/basics/_committing/goal.txt
gitgud/skills/basics/_committing/setup.spec
gitgud/skills/basics/_committing/solution.txt
gitgud/skills/basics/_committing/test.spec
gitgud/skills/basics/_merging/explanation.txt
gitgud/skills/basics/_merging/goal.txt
gitgud/skills/basics/_merging/setup.spec
gitgud/skills/basics/_merging/solution.txt
gitgud/skills/basics/_merging/test.spec
gitgud/skills/basics/_rebasing/explanation.txt
gitgud/skills/basics/_rebasing/goal.txt
gitgud/skills/basics/_rebasing/setup.spec
gitgud/skills/basics/_rebasing/solution.txt
gitgud/skills/basics/_rebasing/test.spec
gitgud/skills/extras/__init__.py
gitgud/skills/extras/test_levels.py
gitgud/skills/extras/_octopus/explanation.txt
gitgud/skills/extras/_octopus/goal.txt
gitgud/skills/extras/_octopus/setup.spec
gitgud/skills/extras/_octopus/solution.txt
gitgud/skills/extras/_octopus/test.spec
gitgud/skills/intro/__init__.py
gitgud/skills/intro/test_levels.py
gitgud/skills/intro/_config/explanation.txt
gitgud/skills/intro/_config/goal.txt
gitgud/skills/intro/_config/passed.txt
gitgud/skills/intro/_config/post-setup.txt
gitgud/skills/intro/_config/setup.spec
gitgud/skills/intro/_config/solution.txt
gitgud/skills/intro/_config/status-1.txt
gitgud/skills/intro/_config/status-2.txt
gitgud/skills/intro/_config/test.spec
gitgud/skills/intro/_init/explanation.txt
gitgud/skills/intro/_init/failed.txt
gitgud/skills/intro/_init/goal.txt
gitgud/skills/intro/_init/passed.txt
git_gud-0.4.5.dist-info/LICENSE.md
git_gud-0.4.5.dist-info/METADATA
git_gud-0.4.5.dist-info/WHEEL
git_gud-0.4.5.dist-info/entry_points.txt
git_gud-0.4.5.dist-info/top_level.txt
git_gud-0.4.5.dist-info/RECORD
