Metadata-Version: 2.1
Name: git-gud
Version: 0.4.5
Summary: A command line game to learn git
Home-page: https://github.com/benthayer/git-gud/
Author: Ben Thayer
Author-email: ben@benthayer.com
License: MIT
Requires-Python: >=3.6
License-File: LICENSE.md
Requires-Dist: gitpython==3.1.7
Requires-Dist: importlib-resources
Requires-Dist: pyyaml
